RTL/sim/tb_u6_contention.v
`timescale 1ns/1ps
//==============================================================================
// U6 address-low buffer direction control: '245 (A4092) vs '543 as-built (A4770)
// vs the A4770_DIRFIX rework (the REAL registered break-before-make logic from
// A4092.v).  Injects the MASTER(chip) vs BMASTER(CPLD) skew and measures the
// "both directions ON" window at the slave->master edge.
//==============================================================================
module u6dut #(parameter TPD=7) (input MASTER_n, input CLK, input integer MODE, output overlap);
    wire BMASTER;  assign #TPD BMASTER = ~MASTER_n;   // CPLD output, lags raw 770 pin
    wire ABOEL_n = 1'b0;

    // MODE 2 = the actual rework logic (copy of A4092.v A4770_DIRFIX block)
    reg       dir_ab_en = 1'b0;
    reg [1:0] dir_guard = 2'b00;
    always @(posedge CLK or posedge MASTER_n) begin
        if (MASTER_n) begin dir_ab_en <= 1'b0; dir_guard <= 2'b00; end
        else begin
            if (dir_guard[1]) dir_ab_en <= 1'b1;
            else              dir_guard <= dir_guard + 1'b1;
        end
    end
    wire SCSI_DIR_AB_n = ~dir_ab_en;   // = CEAB for the address buffers in the fix

    reg drvA, drvB;
    always @(*) case (MODE)
        0: begin drvB = ~MASTER_n      & ~ABOEL_n; drvA = ~BMASTER & ~ABOEL_n; end // '543 as-built
        1: begin drvB =  BMASTER       & ~ABOEL_n; drvA = ~BMASTER & ~ABOEL_n; end // '245 single DIR
        2: begin drvB = ~SCSI_DIR_AB_n & ~ABOEL_n; drvA = ~BMASTER & ~ABOEL_n; end // A4770_DIRFIX
        default: begin drvB = 1'b0; drvA = 1'b0; end
    endcase
    assign overlap = drvA & drvB;
endmodule

module tb_u6_contention;
    reg MASTER_n; integer MODE; reg CLK = 0;
    always #10 CLK = ~CLK;   // 50 MHz CLK_50M
    wire ov3, ov7, ov12;
    u6dut #(.TPD(3))  d3 (.MASTER_n(MASTER_n), .CLK(CLK), .MODE(MODE), .overlap(ov3));
    u6dut #(.TPD(7))  d7 (.MASTER_n(MASTER_n), .CLK(CLK), .MODE(MODE), .overlap(ov7));
    u6dut #(.TPD(12)) d12(.MASTER_n(MASTER_n), .CLK(CLK), .MODE(MODE), .overlap(ov12));
    time s3,s7,s12; real w3,w7,w12;
    always @(posedge ov3)  s3=$time;  always @(negedge ov3)  w3 =$time-s3;
    always @(posedge ov7)  s7=$time;  always @(negedge ov7)  w7 =$time-s7;
    always @(posedge ov12) s12=$time; always @(negedge ov12) w12=$time-s12;

    task do_edge; begin MASTER_n=1; #80; w3=0; w7=0; w12=0; MASTER_n=0; #120; MASTER_n=1; #40; end endtask

    real w245, w543, wfix;
    initial begin
        $dumpfile("u6_contention.vcd"); $dumpvars(0, tb_u6_contention);
        $display("=== U6: 'both directions ON' window at slave->master vs CPLD skew Tpd ===");
        MODE=1; do_edge; w245=w7; $display("  245 transceiver (A4092, single DIR)     : Tpd3=%0.1f  Tpd7=%0.1f  Tpd12=%0.1f ns", w3,w7,w12);
        MODE=0; do_edge; w543=w7; $display("  543 as-built    (A4770, CEAB=MASTER)    : Tpd3=%0.1f  Tpd7=%0.1f  Tpd12=%0.1f ns", w3,w7,w12);
        MODE=2; do_edge; wfix=w7; $display("  A4770_DIRFIX rework (registered B-b-M)   : Tpd3=%0.1f  Tpd7=%0.1f  Tpd12=%0.1f ns", w3,w7,w12);
        $display("=== window>0 => buffer drives A->B and B->A at once (out-of-spec; '245 cannot) ===");
        if (w245==0.0 && w543>0.0 && wfix==0.0)
            $display("tb_u6_contention: PASS ('543-only overlap=%0.1fns; '245 clean; DIRFIX rework closes it)", w543);
        else
            $display("tb_u6_contention: FAIL (245=%0.1f 543=%0.1f fix=%0.1f)", w245,w543,wfix);
        $finish;
    end
endmodule

RTL/sim/u6_contention.vcd
$date
	Sun Jun  7 21:23:35 2026
$end
$version
	Icarus Verilog
$end
$timescale
	1ps
$end
$scope module tb_u6_contention $end
$var wire 1 ! ov7 $end
$var wire 1 " ov3 $end
$var wire 1 # ov12 $end
$var reg 1 $ CLK $end
$var reg 1 % MASTER_n $end
$var reg 64 & s12 [63:0] $end
$var reg 64 ' s3 [63:0] $end
$var reg 64 ( s7 [63:0] $end
$var integer 32 ) MODE [31:0] $end
$var real 1 * w12 $end
$var real 1 + w245 $end
$var real 1 , w3 $end
$var real 1 - w543 $end
$var real 1 . w7 $end
$var real 1 / wfix $end
$scope module d12 $end
$var wire 1 0 ABOEL_n $end
$var wire 1 1 BMASTER $end
$var wire 1 $ CLK $end
$var wire 1 % MASTER_n $end
$var wire 32 2 MODE [31:0] $end
$var wire 1 3 SCSI_DIR_AB_n $end
$var wire 1 # overlap $end
$var parameter 32 4 TPD $end
$var reg 1 5 dir_ab_en $end
$var reg 2 6 dir_guard [1:0] $end
$var reg 1 7 drvA $end
$var reg 1 8 drvB $end
$upscope $end
$scope module d3 $end
$var wire 1 9 ABOEL_n $end
$var wire 1 : BMASTER $end
$var wire 1 $ CLK $end
$var wire 1 % MASTER_n $end
$var wire 32 ; MODE [31:0] $end
$var wire 1 < SCSI_DIR_AB_n $end
$var wire 1 " overlap $end
$var parameter 32 = TPD $end
$var reg 1 > dir_ab_en $end
$var reg 2 ? dir_guard [1:0] $end
$var reg 1 @ drvA $end
$var reg 1 A drvB $end
$upscope $end
$scope module d7 $end
$var wire 1 B ABOEL_n $end
$var wire 1 C BMASTER $end
$var wire 1 $ CLK $end
$var wire 1 % MASTER_n $end
$var wire 32 D MODE [31:0] $end
$var wire 1 E SCSI_DIR_AB_n $end
$var wire 1 ! overlap $end
$var parameter 32 F TPD $end
$var reg 1 G dir_ab_en $end
$var reg 2 H dir_guard [1:0] $end
$var reg 1 I drvA $end
$var reg 1 J drvB $end
$upscope $end
$scope task do_edge $end
$upscope $end
$upscope $end
$enddefinitions $end
$comment Show the parameter values. $end
$dumpall
b111 F
b11 =
b1100 4
$end
#0
$dumpvars
xJ
xI
b0 H
0G
1E
b1 D
xC
0B
xA
x@
b0 ?
0>
1<
b1 ;
x:
09
x8
x7
b0 6
05
13
b1 2
x1
00
r0 /
r0 .
r0 -
r0 ,
r0 +
r0 *
b1 )
bx (
bx '
bx &
1%
0$
x#
x"
x!
$end
#3000
0"
1@
0A
0:
#7000
0!
1I
0J
0C
#10000
1$
#12000
0#
17
08
01
#20000
0$
#30000
1$
#40000
0$
#50000
1$
#60000
0$
#70000
1$
#80000
0$
0%
#83000
0@
1A
1:
#87000
0I
1J
1C
#90000
b1 6
b1 H
b1 ?
1$
#92000
07
18
11
#100000
0$
#110000
b10 ?
b10 H
b10 6
1$
#120000
0$
#130000
03
0E
0<
15
1G
1>
1$
#140000
0$
#150000
1$
#160000
0$
#170000
1$
#180000
0$
#190000
1$
#200000
13
1E
1<
b0 6
05
b0 H
0G
b0 ?
0>
0$
1%
#203000
1@
0A
0:
#207000
1I
0J
0C
#210000
1$
#212000
17
08
01
#220000
0$
#230000
1$
#240000
0$
b0 )
b0 2
b0 ;
b0 D
#250000
1$
#260000
0$
#270000
1$
#280000
0$
#290000
1$
#300000
0$
#310000
1$
#320000
b101000000 &
b101000000 '
b101000000 (
1#
1"
1!
18
1A
1J
0$
0%
#323000
r3 ,
0"
0@
1:
#327000
r7 .
0!
0I
1C
#330000
b1 ?
b1 H
b1 6
1$
#332000
r12 *
0#
07
11
#340000
0$
#350000
b10 6
b10 H
b10 ?
1$
#360000
0$
#370000
0<
0E
03
1>
1G
15
1$
#380000
0$
#390000
1$
#400000
0$
#410000
1$
#420000
0$
#430000
1$
#440000
1<
1E
13
b0 ?
0>
b0 H
0G
b0 6
05
08
0A
0J
0$
1%
#443000
1@
0:
#447000
1I
0C
#450000
1$
#452000
17
01
#460000
0$
#470000
1$
#480000
0$
b10 )
b10 2
b10 ;
b10 D
r7 -
#490000
1$
#500000
0$
#510000
1$
#520000
0$
#530000
1$
#540000
0$
#550000
1$
#560000
0$
0%
r0 *
r0 .
r0 ,
#563000
0@
1:
#567000
0I
1C
#570000
b1 6
b1 H
b1 ?
1$
#572000
07
11
#580000
0$
#590000
b10 ?
b10 H
b10 6
1$
#600000
0$
#610000
18
1J
1A
03
0E
0<
15
1G
1>
1$
#620000
0$
#630000
1$
#640000
0$
#650000
1$
#660000
0$
#670000
1$
#680000
08
0J
0A
13
1E
1<
b0 6
05
b0 H
0G
b0 ?
0>
0$
1%
#683000
1@
0:
#687000
1I
0C
#690000
1$
#692000
17
01
